compas_eve/__init__.py
compas_eve/__main__.py
compas_eve/core.py
compas_eve/event_emitter.py
compas_eve/codecs/__init__.py
compas_eve/codecs/conversions.py
compas_eve/ghpython/__init__.py
compas_eve/ghpython/background.py
compas_eve/ghpython/components/___init__.py
compas_eve/ghpython/components/Ce_BackgroundTask/code.py
compas_eve/ghpython/components/Ce_BackgroundTask/icon.png
compas_eve/ghpython/components/Ce_BackgroundTask/metadata.json
compas_eve/ghpython/components/Ce_Message/code.py
compas_eve/ghpython/components/Ce_Message/icon.png
compas_eve/ghpython/components/Ce_Message/metadata.json
compas_eve/ghpython/components/Ce_MqttConnect/code.py
compas_eve/ghpython/components/Ce_MqttConnect/icon.png
compas_eve/ghpython/components/Ce_MqttConnect/metadata.json
compas_eve/ghpython/components/Ce_Publish/code.py
compas_eve/ghpython/components/Ce_Publish/icon.png
compas_eve/ghpython/components/Ce_Publish/metadata.json
compas_eve/ghpython/components/Ce_Subscribe/code.py
compas_eve/ghpython/components/Ce_Subscribe/icon.png
compas_eve/ghpython/components/Ce_Subscribe/metadata.json
compas_eve/ghpython/yak_template/icon.png
compas_eve/ghpython/yak_template/manifest.yml
compas_eve/memory/__init__.py
compas_eve/mqtt/__init__.py
compas_eve/mqtt/mqtt_paho.py
compas_eve/proto/message.proto
compas_eve/proto/message_pb2.py
compas_eve/rhino/__init__.py
compas_eve/rhino/install.py
compas_eve-2.1.1.dist-info/licenses/AUTHORS.md
compas_eve-2.1.1.dist-info/licenses/LICENSE
compas_eve-2.1.1.dist-info/METADATA
compas_eve-2.1.1.dist-info/WHEEL
compas_eve-2.1.1.dist-info/entry_points.txt
compas_eve-2.1.1.dist-info/top_level.txt
compas_eve-2.1.1.dist-info/RECORD
