Metadata-Version: 2.4
Name: compas_eve
Version: 2.1.1
Summary: COMPAS Event Extensions: adds event-based communication infrastructure to the COMPAS framework.
Author-email: Gonzalo Casas <casas@arch.ethz.ch>, Chen Kasirer <kasirer@arch.ethz.ch>
License: MIT License
Project-URL: Homepage, https://github.com/compas-dev/compas_eve
Project-URL: Documentation, https://compas.dev/compas_eve
Project-URL: Repository, https://github.com/compas-dev/compas_eve
Project-URL: Changelog, https://github.com/compas-dev/compas_eve/blob/main/CHANGELOG.md
Project-URL: Issues, https://github.com/compas-dev/compas_eve/issues
Project-URL: Forum, https://forum.compas-framework.org/
Keywords: events,event-driven,compas,architecture,distributed systems
Classifier: Development Status :: 4 - Beta
Classifier: Topic :: Scientific/Engineering
Classifier: Operating System :: Unix
Classifier: Operating System :: POSIX
Classifier: Operating System :: Microsoft :: Windows
Classifier: Programming Language :: Python
Classifier: Programming Language :: Python :: 3
Classifier: Programming Language :: Python :: 3.10
Classifier: Programming Language :: Python :: 3.11
Classifier: Programming Language :: Python :: 3.12
Classifier: Programming Language :: Python :: 3.13
Classifier: Programming Language :: Python :: 3.14
Requires-Python: >=3.9
License-File: LICENSE
License-File: AUTHORS.md
Requires-Dist: compas>=1.17.6
Requires-Dist: paho-mqtt<3,>=1
Provides-Extra: dev
Requires-Dist: attrs>=17.4; extra == "dev"
Requires-Dist: black>=22.12.0; extra == "dev"
Requires-Dist: build; extra == "dev"
Requires-Dist: bump-my-version; extra == "dev"
Requires-Dist: compas_invocations2; extra == "dev"
Requires-Dist: compas_pb>=0.4.4; extra == "dev"
Requires-Dist: invoke>=0.14; extra == "dev"
Requires-Dist: pytest-mock; extra == "dev"
Requires-Dist: ruff; extra == "dev"
Requires-Dist: sphinx_compas2_theme; extra == "dev"
Requires-Dist: twine; extra == "dev"
Requires-Dist: wheel; extra == "dev"
Requires-Dist: pythonnet; extra == "dev"
Dynamic: license-file
